attributecode/__init__.py
attributecode/attrib.py
attributecode/attrib_util.py
attributecode/cmd.py
attributecode/model.py
attributecode/util.py
attributecode-2.0.1.dist-info/LICENSE.txt
attributecode-2.0.1.dist-info/METADATA
attributecode-2.0.1.dist-info/RECORD
attributecode-2.0.1.dist-info/WHEEL
attributecode-2.0.1.dist-info/entry_points.txt
attributecode-2.0.1.dist-info/top_level.txt
