Metadata-Version: 2.1
Name: attributecode
Version: 2.0.1
Summary: Generate attribution document with input of CSV/Excel/JSON.
Home-page: https://github.com/nexB/attributecode
Author: nexB. Inc. and others
Author-email: info@aboutcode.org
License: UNKNOWN
Platform: UNKNOWN
Classifier: Development Status :: 4 - Beta
Classifier: Programming Language :: Python :: 3.6
Classifier: Intended Audience :: Developers
Classifier: License :: OSI Approved :: Apache Software License
Classifier: Topic :: Software Development
Classifier: Topic :: Software Development :: Documentation
Classifier: Topic :: System :: Software Distribution
Classifier: Topic :: Utilities
Provides-Extra: testing
Requires-Dist: jinja2 (<3.0,>=2.9)
Requires-Dist: click
Requires-Dist: PyYAML (<=3.13,>=3.11)
Requires-Dist: saneyaml
Requires-Dist: boolean.py (<4.0,>=3.5)
Requires-Dist: license-expression (>=0.94)
Requires-Dist: packageurl-python (>=0.9.0)
Provides-Extra: testing
Requires-Dist: pytest (>=6); extra == 'testing'
Requires-Dist: pytest-xdist (>=2); extra == 'testing'
Requires-Dist: colorama; extra == 'testing'
Requires-Dist: py; extra == 'testing'
Requires-Dist: mock; extra == 'testing'
